{
  "ComponentIndexes": {},
  "ControlUniqueGuids": {},
  "ControlUniqueIds": {
    "App": 1,
    "AppTitle1": 40,
    "AppTxt2": 7,
    "BottomBorder1": 48,
    "BottomBorder2": 32,
    "BottomHUD1": 71,
    "Burger_DropDown": 73,
    "Button1": 37,
    "CHome": 60,
    "DataCardKey1": 12,
    "DataCardKey2": 17,
    "DataCardKey3": 22,
    "DataCardKey4": 27,
    "DataCardValue1": 13,
    "DataCardValue2": 18,
    "DataCardValue3": 23,
    "DataCardValue4": 28,
    "DHome": 53,
    "Email_DataCard1": 20,
    "ErrorMessage1": 14,
    "ErrorMessage2": 19,
    "ErrorMessage3": 24,
    "ErrorMessage4": 29,
    "HamburgerIcon1": 62,
    "HamburgerIcon1_1": 55,
    "HamburgerIcon1_2": 75,
    "Header": 52,
    "Header2": 33,
    "HeaderHUD1": 72,
    "Icon1": 74,
    "LeftBorder1": 38,
    "LeftBorder2": 5,
    "Login": 35,
    "LoginBtn1": 46,
    "LoginTxt1": 41,
    "MobileNo_DataCard1": 15,
    "Password_DataCard1": 25,
    "PasswordField1": 51,
    "PasswordInput1": 45,
    "PasswordTxt1": 44,
    "QrScanner1": 66,
    "QrScanner1_1": 56,
    "Rectangle2": 61,
    "Rectangle2_1": 54,
    "Rectangle3": 67,
    "Rectangle3_1": 68,
    "Rectangle3_2": 69,
    "Rectangle3_3": 57,
    "Rectangle3_4": 58,
    "Rectangle3_5": 59,
    "RightBorder1": 39,
    "RightBorder2": 6,
    "ScreenBorder1": 49,
    "ScreenBorder2": 34,
    "Search1": 70,
    "SearchBar1": 63,
    "SearchBarLine1": 65,
    "SearchIcon1": 64,
    "Sign Up": 3,
    "sign_up_btn": 30,
    "SignUpForm": 9,
    "SignUpTxt1": 8,
    "StarVisible1": 11,
    "StarVisible2": 16,
    "StarVisible3": 21,
    "StarVisible4": 26,
    "TopBox1": 36,
    "TopBox2": 4,
    "Txt2Login1": 31,
    "Txt2SignUp1": 47,
    "UNameEmailField1": 50,
    "UNameEmailInput1": 43,
    "UNameEmailTxt1": 42,
    "Username_DataCard1": 10
  },
  "FunctionParamsInvariantScripts": {},
  "FunctionParamsInvariantScriptsOnInstances": {},
  "HeaderLastSavedDateTimeUTC": "01/14/2023 09:35:13",
  "IsLegacyComponentAllowGlobalScopeCase": false,
  "LocalConnectionIDReferences": {
    "1a3ad4d4-a966-4ef3-9557-bb33f76d0531": "\"/providers/microsoft.powerapps/apis/shared_onedriveforbusiness/connections/1c48a45f3dba463db82827fb3ac8a252\"",
    "30907c22-7f48-49da-a3b9-27539d9f4aba": "\"/providers/microsoft.powerapps/apis/shared_excel/connections/bfa28764ed1d43c194c71f2002ea51c8\"",
    "342b4c6d-4705-4111-85d2-920cfef8dfdc": "\"/providers/microsoft.powerapps/apis/shared_excel/connections/bfa28764ed1d43c194c71f2002ea51c8\"",
    "4abbe65a-7114-438c-8059-a840eb2cccf1": "\"/providers/microsoft.powerapps/apis/shared_onedriveforbusiness/connections/1c48a45f3dba463db82827fb3ac8a252\"",
    "587b6246-f6b3-445f-934c-838536ba1d49": "\"/providers/microsoft.powerapps/apis/shared_onedriveforbusiness/connections/1c48a45f3dba463db82827fb3ac8a252\"",
    "a9e7254a-8c5c-45a2-a88c-e786287ca2fc": "\"/providers/microsoft.powerapps/apis/shared_excel/connections/bfa28764ed1d43c194c71f2002ea51c8\"",
    "c0a6e8dd-01c6-4e66-ae13-513cd289e4db": "\"/providers/microsoft.powerapps/apis/shared_excel/connections/bfa28764ed1d43c194c71f2002ea51c8\"",
    "d7331abf-3c29-446c-8a72-49017b85ee87": "\"/providers/microsoft.powerapps/apis/shared_onedriveforbusiness/connections/1c48a45f3dba463db82827fb3ac8a252\""
  },
  "LocalDatabaseReferencesAsEmpty": false,
  "LocalResourceFileNames": {},
  "LocalResourceRootPaths": {},
  "OrderComponentMetadata": {},
  "OrderComponentTemplate": {},
  "OrderDataSource": {
    "customer": 0,
    "CustomGallerySample": 1,
    "PurchaseTransaction": 2,
    "Reward": 3,
    "RewardTransaction": 4
  },
  "OrderGroupControls": {
    "BottomHUD1": {
      "Rectangle3": 0,
      "Rectangle3_1": 1,
      "Rectangle3_2": 2
    },
    "Header": {
      "AppTitle1": 0,
      "TopBox1": 1
    },
    "Header2": {
      "AppTxt2": 0,
      "TopBox2": 1
    },
    "HeaderHUD1": {
      "HamburgerIcon1": 1,
      "Rectangle2": 0
    },
    "PasswordField1": {
      "PasswordInput1": 0,
      "PasswordTxt1": 1
    },
    "ScreenBorder1": {
      "BottomBorder1": 2,
      "LeftBorder1": 0,
      "RightBorder1": 1
    },
    "ScreenBorder2": {
      "BottomBorder2": 2,
      "LeftBorder2": 0,
      "RightBorder2": 1
    },
    "Search1": {
      "SearchBar1": 0,
      "SearchBarLine1": 2,
      "SearchIcon1": 1
    },
    "UNameEmailField1": {
      "UNameEmailInput1": 1,
      "UNameEmailTxt1": 0
    }
  },
  "OrderPcfTemplate": {},
  "OrderTemplate": {},
  "OrderXMLTemplate": {
    "barcodeScanner": 6,
    "button": 5,
    "form": 3,
    "icon": 1,
    "label": 2,
    "rectangle": 0,
    "text": 4
  },
  "OverridablePropertiesEntry": {
    "App": {},
    "AppTitle1": {},
    "AppTxt2": {},
    "BottomBorder1": {},
    "BottomBorder2": {},
    "BottomHUD1": {},
    "Burger_DropDown": {},
    "Button1": {},
    "CHome": {},
    "DataCardKey1": {},
    "DataCardKey2": {},
    "DataCardKey3": {},
    "DataCardKey4": {},
    "DataCardValue1": {},
    "DataCardValue2": {},
    "DataCardValue3": {},
    "DataCardValue4": {},
    "DHome": {},
    "Email_DataCard1": {},
    "ErrorMessage1": {},
    "ErrorMessage2": {},
    "ErrorMessage3": {},
    "ErrorMessage4": {},
    "HamburgerIcon1": {},
    "HamburgerIcon1_1": {},
    "HamburgerIcon1_2": {},
    "Header": {},
    "Header2": {},
    "HeaderHUD1": {},
    "Icon1": {},
    "LeftBorder1": {},
    "LeftBorder2": {},
    "Login": {},
    "LoginBtn1": {},
    "LoginTxt1": {},
    "MobileNo_DataCard1": {},
    "Password_DataCard1": {},
    "PasswordField1": {},
    "PasswordInput1": {},
    "PasswordTxt1": {},
    "QrScanner1": {},
    "QrScanner1_1": {},
    "Rectangle2": {},
    "Rectangle2_1": {},
    "Rectangle3": {},
    "Rectangle3_1": {},
    "Rectangle3_2": {},
    "Rectangle3_3": {},
    "Rectangle3_4": {},
    "Rectangle3_5": {},
    "RightBorder1": {},
    "RightBorder2": {},
    "ScreenBorder1": {},
    "ScreenBorder2": {},
    "Search1": {},
    "SearchBar1": {},
    "SearchBarLine1": {},
    "SearchIcon1": {},
    "Sign Up": {},
    "sign_up_btn": {},
    "SignUpForm": {},
    "SignUpTxt1": {},
    "StarVisible1": {},
    "StarVisible2": {},
    "StarVisible3": {},
    "StarVisible4": {},
    "TopBox1": {},
    "TopBox2": {},
    "Txt2Login1": {},
    "Txt2SignUp1": {},
    "UNameEmailField1": {},
    "UNameEmailInput1": {},
    "UNameEmailTxt1": {},
    "Username_DataCard1": {}
  },
  "PCFDynamicSchemaForIRRetrievalEntry": {},
  "PublishOrderIndices": {
    "App": 0,
    "AppTitle1": 5,
    "AppTxt2": 20,
    "BottomBorder1": 16,
    "BottomBorder2": 47,
    "BottomHUD1": 51,
    "Burger_DropDown": 0,
    "Button1": 15,
    "CHome": 2,
    "DataCardKey1": 27,
    "DataCardKey2": 32,
    "DataCardKey3": 37,
    "DataCardKey4": 42,
    "DataCardValue1": 28,
    "DataCardValue2": 33,
    "DataCardValue3": 38,
    "DataCardValue4": 43,
    "DHome": 15,
    "Email_DataCard1": 35,
    "ErrorMessage1": 29,
    "ErrorMessage2": 34,
    "ErrorMessage3": 39,
    "ErrorMessage4": 44,
    "HamburgerIcon1": 49,
    "HamburgerIcon1_1": 61,
    "HamburgerIcon1_2": 67,
    "Header": 3,
    "Header2": 21,
    "HeaderHUD1": 52,
    "Icon1": 66,
    "LeftBorder1": 1,
    "LeftBorder2": 18,
    "Login": 22,
    "LoginBtn1": 13,
    "LoginTxt1": 6,
    "MobileNo_DataCard1": 30,
    "Password_DataCard1": 40,
    "PasswordField1": 11,
    "PasswordInput1": 12,
    "PasswordTxt1": 10,
    "QrScanner1": 56,
    "QrScanner1_1": 62,
    "Rectangle2": 48,
    "Rectangle2_1": 60,
    "Rectangle3": 57,
    "Rectangle3_1": 58,
    "Rectangle3_2": 59,
    "Rectangle3_3": 63,
    "Rectangle3_4": 64,
    "Rectangle3_5": 65,
    "RightBorder1": 4,
    "RightBorder2": 19,
    "ScreenBorder1": 2,
    "ScreenBorder2": 22,
    "Search1": 50,
    "SearchBar1": 53,
    "SearchBarLine1": 55,
    "SearchIcon1": 54,
    "Sign Up": 28,
    "sign_up_btn": 45,
    "SignUpForm": 24,
    "SignUpTxt1": 23,
    "StarVisible1": 26,
    "StarVisible2": 31,
    "StarVisible3": 36,
    "StarVisible4": 41,
    "TopBox1": 0,
    "TopBox2": 17,
    "Txt2Login1": 46,
    "Txt2SignUp1": 14,
    "UNameEmailField1": 8,
    "UNameEmailInput1": 9,
    "UNameEmailTxt1": 7,
    "Username_DataCard1": 25
  },
  "ResourcesJsonIndices": {
    "Image-SampleImage": 0
  },
  "RuleScreenIdWithoutScreen": {},
  "TemplateVersions": {},
  "VolatileProperties": {
    "AnalysisLoadTime": 0.4550269,
    "ControlCount": {
      "barcodeScanner": 2,
      "button": 3,
      "form": 1,
      "group": 9,
      "icon": 12,
      "label": 20,
      "rectangle": 10,
      "screen": 5,
      "text": 7,
      "typedDataCard": 4
    },
    "DeserializationLoadTime": 0.9804013,
    "ErrorCount": 0
  },
  "WasLocalDatabaseReferencesEmpty": true
}